gpapidl/__init__.py
gpapidl/config.py
gpapidl/device.properties
gpapidl/googleplay.py
gpapidl/googleplay_pb2.py
gpapidl/utils.py
gpapidl-1.0.1.dist-info/LICENSE.md
gpapidl-1.0.1.dist-info/METADATA
gpapidl-1.0.1.dist-info/WHEEL
gpapidl-1.0.1.dist-info/top_level.txt
gpapidl-1.0.1.dist-info/RECORD
